qcop/__init__.py
qcop/exceptions.py
qcop/main.py
qcop/py.typed
qcop/utils.py
qcop/adapters/__init__.py
qcop/adapters/base.py
qcop/adapters/crest.py
qcop/adapters/file.py
qcop/adapters/geometric.py
qcop/adapters/qcengine.py
qcop/adapters/terachem.py
qcop/adapters/terachem_fe.py
qcop/adapters/terachem_pbs.py
qcop/adapters/utils.py
qcop/adapters/xtb.py
qcop-0.12.0.dist-info/METADATA
qcop-0.12.0.dist-info/WHEEL
qcop-0.12.0.dist-info/licenses/LICENSE
qcop-0.12.0.dist-info/RECORD
