Metadata-Version: 2.4
Name: qcop
Version: 0.12.0
Summary: A package for operating Quantum Chemistry programs using qcio standardized data structures. Compatible with TeraChem, psi4, QChem, NWChem, ORCA, Molpro, geomeTRIC and many more.
Project-URL: Homepage, https://github.com/coltonbh/qcop
Project-URL: Source, https://github.com/coltonbh/qcio
Project-URL: Repository, https://github.com/coltonbh/qcop
Project-URL: Changelog, https://github.com/coltonbh/qcop/blob/master/CHANGELOG.md
Project-URL: Bug Tracker, https://github.com/coltonbh/qcop/issues
Project-URL: Documentation, https://qcop.coltonhicks.com
Author-email: Colton Hicks <github@coltonhicks.com>
License: The MIT License (MIT)
License-File: LICENSE
Classifier: Development Status :: 4 - Beta
Classifier: Intended Audience :: Developers
Classifier: Intended Audience :: Science/Research
Classifier: License :: OSI Approved :: MIT License
Classifier: Natural Language :: English
Classifier: Programming Language :: Python :: 3.10
Classifier: Programming Language :: Python :: 3.11
Classifier: Programming Language :: Python :: 3.12
Classifier: Programming Language :: Python :: 3.13
Classifier: Programming Language :: Python :: 3.14
Classifier: Topic :: Scientific/Engineering
Classifier: Topic :: Software Development :: Libraries
Requires-Python: >=3.10
Requires-Dist: qccodec>=0.9.0
Requires-Dist: qcio>=0.16.0
Requires-Dist: tomli-w<2,>=1.0.0
Provides-Extra: all
Requires-Dist: geometric<2,>=1.0.1; extra == 'all'
Requires-Dist: qcelemental<0.27,>=0.26.0; extra == 'all'
Requires-Dist: qcengine<0.28,>=0.27.0; extra == 'all'
Requires-Dist: tcpb>=0.14.1; extra == 'all'
Provides-Extra: geometric
Requires-Dist: geometric<2,>=1.0.1; extra == 'geometric'
Provides-Extra: qcengine
Requires-Dist: qcelemental<0.27,>=0.26.0; extra == 'qcengine'
Requires-Dist: qcengine<0.28,>=0.27.0; extra == 'qcengine'
